dbxs/__init__.py
dbxs/__main__.py
dbxs/_access.py
dbxs/_enumerate.py
dbxs/_repository.py
dbxs/_testing.py
dbxs/_typing_compat.py
dbxs/async_dbapi.py
dbxs/dbapi.py
dbxs/py.typed
dbxs/testing.py
dbxs/adapters/__init__.py
dbxs/adapters/async_mysql.py
dbxs/adapters/async_pool.py
dbxs/adapters/async_psycopg.py
dbxs/adapters/dbapi_twisted.py
dbxs/test/__init__.py
dbxs/test/common_adapter_tests.py
dbxs/test/some_simple_queries.py
dbxs/test/sqla_simple_queries.py
dbxs/test/test_access.py
dbxs/test/test_enumerate.py
dbxs/test/test_mysql.py
dbxs/test/test_pg.py
dbxs/test/test_sync_adapter.py
dbxs/test/test_testing.py
dbxs-2025.8.20.dist-info/licenses/LICENSE
dbxs-2025.8.20.dist-info/WHEEL
dbxs-2025.8.20.dist-info/METADATA
dbxs-2025.8.20.dist-info/RECORD
