Metadata-Version: 2.4
Name: dbxs
Version: 2025.8.20
Summary: DBXS (“D.B. Access”) is an SQL database access layer for Python.
Author-email: Glyph <code@glyph.im>
Requires-Python: >=3.9
Classifier: License :: OSI Approved :: MIT License
License-File: LICENSE
Requires-Dist: twisted
Project-URL: Home, https://github.com/glyph/DBXS
